deep_compare/__init__.py
deep_compare/compare_variables.py
deep_compare-1.0.5.dist-info/LICENSE
deep_compare-1.0.5.dist-info/METADATA
deep_compare-1.0.5.dist-info/WHEEL
deep_compare-1.0.5.dist-info/top_level.txt
deep_compare-1.0.5.dist-info/RECORD
