Metadata-Version: 2.1
Name: deep-compare
Version: 1.0.5
Summary: A package to compare variables irrespective of their datatype
Home-page: https://github.com/lavanyavijayk/deep-compare
Author: Lavanya Vijayakrishnan
Author-email: lavanyavijayakrishnan@gmail.com
License: UNKNOWN
Platform: UNKNOWN
Classifier: Programming Language :: Python :: 3
Classifier: License :: OSI Approved :: MIT License
Classifier: Operating System :: OS Independent
Requires-Python: >=3.7
